{
  "title": [
    "Шрī Шікша̄штакам"
  ],
  "author": [
    "Шрīла Бгактівінод Тха̄кур"
  ],
  "subtitle": [
    "Song 7c"
  ],
  "verses": [
    {
      "number": "1",
      "text": [
        "сакхі ґо кемоте дгорібо пара̄н",
        "німеша хоіло джуґера сама̄н"
      ],
      "translation": [
        "Oh my dear girlfriend! How will I  maintain my life? The passing of a mere moment has become like a vast age of time."
      ]
    },
    {
      "number": "2",
      "text": [
        "шра̄ванера дга̄ра̄,    а̄нкхі-барішой,",
        "    шюнья бгело дгара̄-тала",
        "ґовінда-вірахе,    пра̄на на̄хі рохе,",
        "    кемоне ба̄нчібо боло"
      ],
      "translation": [
        "Tears flow from my eyes like torrents of rain in the month of Śrāvaṇa, and the face of the earth has become totally void. In separation from Govinda my life cannot go on... please, tell how I will be able to live."
      ]
    },
    {
      "number": "3",
      "text": [
        "бгакатівінода,    астхіра хоія,",
        "    пунах на̄ма̄шроя корі’",
        "да̄ке ра̄дга̄на̄тха,    дія дарашяна,",
        "    пра̄на ра̄кхо, нахе морі"
      ],
      "translation": [
        "Bhakti Vinod has become very restless and again takes shelter of the holy name, calling out, “Oh Lord of Rādhā! By bestowing Your audience, please save my life! By Your mercy alone I shall not perish!”",
        "Footnote to verse 1: *Śrīla Śrīdhar Mahārāja advised not to sing ‘sakhi go’ but ‘bandhu he’ instead.*"
      ]
    }
  ],
  "attributes": {
    "page": "191"
  }
}