{
  "meta": null,
  "title": [
    "А̄тма-самарпане"
  ],
  "author": [
    "Шрīла Бгактівінод Тха̄кур"
  ],
  "subtitle": [],
  "verses": [
    {
      "number": "1",
      "text": [
        "а̄тма-самарпане ґела̄ абгіма̄на",
        "на̄хі карабу ніджа ракша̄-відга̄н"
      ],
      "translation": [
        "Surrendering my soul unto You has lifted from me the burden of false pride. No longer will I try to provide for my own safety."
      ]
    },
    {
      "number": "2",
      "text": [
        "туя дгана джа̄ні’ туху ра̄кхобі, на̄тх!",
        "па̄лья ґодгана джа̄ні корі’ туя са̄тх"
      ],
      "translation": [
        "I know that You will give protection to Your treasured possessions, Oh Lord. I now understand the mentality of Your treasured cows safely maintained by Your side."
      ]
    },
    {
      "number": "3",
      "text": [
        "чара̄обі ма̄дгава! ямуна̄-тīре",
        "бамші ба̄джа̄ото да̄кобі дгīре"
      ],
      "translation": [
        "When You lead Your herds to pasture, Oh Mādhava, on the banks of the Yamunā river, You will call to them by softly playing on Your flute."
      ]
    },
    {
      "number": "4",
      "text": [
        "ага-бака ма̄рато ракша̄-відга̄на",
        "карабі сада̄ туху ґокула-ка̄на!"
      ],
      "translation": [
        "By slaying great demons such as Aghāsura and Bakāsura You will always provide full protection, Oh Kān of Gokul!"
      ]
    },
    {
      "number": "5",
      "text": [
        "ракша̄ карабі туху нішчой джа̄ні",
        "па̄на карабу ха̄м джа̄муна-па̄ні"
      ],
      "translation": [
        "Fearless and confident of Your protection, I will drink the waters of the Yamunā."
      ]
    },
    {
      "number": "6",
      "text": [
        "ка̄лīя-докха карабі віна̄шя",
        "шодгобі надī-джала, ба̄да̄обі а̄шя"
      ],
      "translation": [
        "The Kālīya serpent’s venom poisoned the Yamunā’s waters, yet that poison will be vanquished. You will purify the Yamunā, and by such heroic deeds enhance our faith."
      ]
    },
    {
      "number": "7",
      "text": [
        "піято да̄ва̄нала ра̄кхобі мой",
        "‘ґопа̄ла’, ‘ґовінда’ на̄ма тава хой"
      ],
      "translation": [
        "You will surely protect me by swallowing the forest fire. Thus You are called Gopāl (protector of the cows) and Govinda (pleaser of the cows)."
      ]
    },
    {
      "number": "8",
      "text": [
        "сура-паті-дурматі-на̄шя віча̄рі’",
        "ра̄кхобе варшане, ґірі-вара-дга̄рі!"
      ],
      "translation": [
        "In order to curb the malice of Indra, king of the demigods, You will protect me from his torrents of rain, Oh lifter of the mighty Govardhan Hill!"
      ]
    },
    {
      "number": "9",
      "text": [
        "чатур-а̄нана корабо джабо чорі",
        "ракша̄ карабі меє, ґокула-харі!"
      ],
      "translation": [
        "When the four-headed Brahmā abducts me along with Your cowherd boyfriends and calves, then also You will surely protect me, Oh Gokul Hari!"
      ]
    },
    {
      "number": "10",
      "text": [
        "бгакатівінода—туя ґокула-дган",
        "ра̄кхобі кешява! корато джатан"
      ],
      "translation": [
        "Bhakti Vinod is now the property of Gokul, Your holy abode. Oh Keśava! Kindly protect him with gentle loving care."
      ]
    }
  ],
  "attributes": {
    "page": "166"
  }
}